repoclean/__init__.py
repoclean/cli.py
repoclean/config_loader.py
repoclean/config_template.py
repoclean/fixer.py
repoclean/gitignore.py
repoclean/hooks.py
repoclean/path_utils.py
repoclean/rules.py
repoclean/scanner.py
repoclean/secrets.py
repoclean/serializer.py
repoclean/tracked_junk.py
repoclean_cli-0.8.0.dist-info/licenses/LICENSE
repoclean_cli-0.8.0.dist-info/METADATA
repoclean_cli-0.8.0.dist-info/WHEEL
repoclean_cli-0.8.0.dist-info/entry_points.txt
repoclean_cli-0.8.0.dist-info/top_level.txt
repoclean_cli-0.8.0.dist-info/RECORD
