Metadata-Version: 2.4
Name: repoclean-cli
Version: 0.8.0
Summary: Repo hygiene scanner and fixer (junk files, secrets, gitignore).
Author: Trishir Kumar Vind
License: MIT
Requires-Python: >=3.9
License-File: LICENSE
Requires-Dist: rich
Requires-Dist: tomli; python_version < "3.11"
Dynamic: license-file
